README.txt
setup.py
gsmirror.egg-info/PKG-INFO
gsmirror.egg-info/SOURCES.txt
gsmirror.egg-info/dependency_links.txt
gsmirror.egg-info/entry_points.txt
gsmirror.egg-info/requires.txt
gsmirror.egg-info/top_level.txt
src/gsmirroring/__init__.py
src/gsmirroring/gsmirror.py
src/gsmirroring/objects.py
src/gsmirroring/site_controller.py
src/gsmirroring/xml_module.py
templates/default_templates/announcement_template.tmpl
templates/default_templates/announcements_page_template.tmpl
templates/default_templates/file_cabinet_template.tmpl
templates/default_templates/listpage_template.tmpl
templates/default_templates/webpage_template.tmpl
templates/staremapy_templates/announcement_template.tmpl
templates/staremapy_templates/announcements_page_template.tmpl
templates/staremapy_templates/file_cabinet_template.tmpl
templates/staremapy_templates/listpage_template.tmpl
templates/staremapy_templates/webpage_template.tmpl
templates/sualeph_templates/announcement_template.tmpl
templates/sualeph_templates/announcements_page_template.tmpl
templates/sualeph_templates/file_cabinet_template.tmpl
templates/sualeph_templates/listpage_template.tmpl
templates/sualeph_templates/webpage_template.tmpl