Metadata-Version: 1.0
Name: gsmirror
Version: 1.0.2
Summary: Google Sites Mirroring & Backup Script
Home-page: http://code.google.com/p/google-sites-mirror/
Author: Jan Rychtar
Author-email: honza.rychtar@gmail.com
License: New BSD License
Platform: UNKNOWN
